lins_barcodeutils/__init__.py
lins_barcodeutils/validators.py
lins_barcodeutils-0.1.0.2.dist-info/METADATA
lins_barcodeutils-0.1.0.2.dist-info/WHEEL
lins_barcodeutils-0.1.0.2.dist-info/top_level.txt
lins_barcodeutils-0.1.0.2.dist-info/RECORD
