Metadata-Version: 2.1
Name: lins-barcodeutils
Version: 0.1.0.2
Summary: Utilitários para se trabalhar com códigos de barras.
Home-page: https://bitbucket.org/grupolinsferrao/pypck-lins_barcodeutils/
Author: Lucas Lehnen
Author-email: lucas@lojaspompeia.com.br
License: MIT
Platform: UNKNOWN
